qulib/Gates.py
qulib/QRegister.py
qulib/__init__.py
qulib-0.2.dist-info/METADATA
qulib-0.2.dist-info/WHEEL
qulib-0.2.dist-info/top_level.txt
qulib-0.2.dist-info/RECORD
